QuantumCheck/__init__.py
QuantumCheck/main.py
QuantumCheck/powerbi_evaluator.py
QuantumCheck/prompts.py
QuantumCheck/python_evaluator.py
QuantumCheck/sql_evaluator.py
QuantumCheck/ssis_evaluator.py
homework_evaluator-0.1.0.dist-info/licenses/LICENSE
homework_evaluator-0.1.0.dist-info/METADATA
homework_evaluator-0.1.0.dist-info/WHEEL
homework_evaluator-0.1.0.dist-info/top_level.txt
homework_evaluator-0.1.0.dist-info/RECORD
