Metadata-Version: 2.4
Name: homework-evaluator
Version: 0.1.0
Summary: A package to evaluate homework submissions in Python, SQL, PowerBI, and SSIS.
Author-email: Qobiljon <qobiljonkhayrullayev@gmail.com>
Project-URL: Homepage, https://github.com/yourusername/homework_evaluator
Project-URL: Repository, https://github.com/yourusername/homework_evaluator
Classifier: Programming Language :: Python :: 3
Classifier: License :: OSI Approved :: MIT License
Classifier: Operating System :: OS Independent
Requires-Python: >=3.6
License-File: LICENSE
Requires-Dist: requests>=2.31.0
Requires-Dist: tenacity>=8.2.3
Requires-Dist: pdf2image>=1.16.3
Requires-Dist: python-dotenv>=1.0.0
Requires-Dist: Pillow>=10.0.0
Dynamic: license-file
